{
                "fromDate": "22-03-2015",
                "toDate": "29-08-2016",
                "debits": "368.441.475",
                "credits": "14.423.292",
                "currency": "USD",
                "soldShipTo": "All",
                "delDocColumnMapping":{
                "delDocId": "test",
                "delDocDate": "dfhj",
                "orderId": "tftjf",
                "total": "yfleuir",
                "total2": null,
                "type": "fjeij",
                "checkbox":"ejuje",
                "shipTo": "test",
                "downloaded": "",
                "printed": false,
                "status":"dbshj",
                "currencyUnit1": null,
                "currencyUnit2": null,
                "purchaseOrderNumber": "ehfukehf",
                "legalDocumentNumber": null,
                "salesOrderType": null,
                "delDocStatus": "dfhkek",
                "payerId": null,
                "eftNumber": null,
                "deliveyDate": null,
                "fiscalYear": null
                },

                "delDocList": [{
                    "delDocId": "936710253",
                    "delDocDate": "02-12-2016",
                    "orderId": "1",
                    "total": -8919237.0,
                    "displayTotal": "-8.919.237",
                    "total2": null,
                    "displayTotal2": null,
                    "type": "YG2",
                    "shipTo": "7901220, DISMACOR S.A., K 16 NRO 20-56, Colombia",
                    "downloaded": true,
                    "printed": true,
                    "currencyUnit": "COP",
                    "currencyUnit2": null,
                    "purchaseOrderNumber": "NC BDP",
                    "legalDocumentNumber": "35-2655",
                    "salesOrderType": "ZOOR",
                    "paydelDoc": "true"
                },
                {
                    "delDocId": "936670263",
                    "delDocDate": "30-11-2015",
                    "orderId": "2",
                    "total": 36928702,
                    "displayTotal": "36.928.702",
                    "total2": null,
                    "displayTotal2": null,
                    "type": "ZF2",
                    "shipTo": "7933464, DISMACOR S.A. BARBOSA, K 10 NRO 20  11, Colombia",
                    "downloaded": true,
                    "printed": false,
                    "currencyUnit": "COP",
                    "currencyUnit2": null,
                    "purchaseOrderNumber": "BARBOSA",
                    "legalDocumentNumber": "35-14602",
                    "salesOrderType": "ZOOR",
                    "cbpdelDocStatus": "01"
                }, 
                {
                    "delDocId": "936659699",
                    "delDocDate": "30-10-2015",
                    "orderId": "3",
                    "total": -12621100,
                    "displayTotal": "-12.621.100",
                    "total2": null,
                    "displayTotal2": null,
                    "type": "YSOU",
                    "shipTo": "7901220, DISMACOR S.A., K 16 NRO 20-56, Colombia",
                    "downloaded": true,
                    "printed": false,
                    "currencyUnit": "COP",
                    "currencyUnit2": null,
                    "purchaseOrderNumber": null,
                    "legalDocumentNumber": "35-2371",
                    "salesOrderType": "ZC"
                }, 
                {
                    "delDocId": "936659698",
                    "delDocDate": "30-10-2015",
                    "orderId": "4",
                    "total": -5655000,
                    "displayTotal": "-5.655.000",
                    "total2": null,
                    "displayTotal2": null,
                    "type": "",
                    "shipTo": "7901220, DISMACOR S.A., K 16 NRO 20-56, Colombia",
                    "downloaded": false,
                    "printed": false,
                    "currencyUnit": "COP",
                    "currencyUnit2": null,
                    "purchaseOrderNumber": null,
                    "legalDocumentNumber": "35-2370",
                    "salesOrderType": "ZC"
                }],
                "resultCount": 4,
                "multipleSoldTo": false,
                "sort": null
            }